numberdividend/__init__.py
numberdividend/__main__.py
numberdividend/controller.py
numberdividend/core.py
numberdividend-0.1.2.dist-info/licenses/LICENSE
numberdividend-0.1.2.dist-info/METADATA
numberdividend-0.1.2.dist-info/WHEEL
numberdividend-0.1.2.dist-info/entry_points.txt
numberdividend-0.1.2.dist-info/top_level.txt
numberdividend-0.1.2.dist-info/RECORD
