Metadata-Version: 2.4
Name: numberdividend
Version: 0.1.2
Summary: A tool for dividend distribution analysis.
Home-page: https://github.com/SaboIch/NumberDividend
Author: Sabolch
Author-email: sabolch.dev@gmail.com
License: MIT
Keywords: dividend distribution analysis
Classifier: Programming Language :: Python :: 3
Classifier: License :: OSI Approved :: MIT License
Classifier: Operating System :: OS Independent
Classifier: Intended Audience :: Developers
Classifier: Natural Language :: English
Requires-Python: >=3.6
License-File: LICENSE
Requires-Dist: pandas>=1.0.0
Requires-Dist: matplotlib>=3.0.0
Requires-Dist: numpy>=1.0.0
Requires-Dist: argparse>=1.4.0
Requires-Dist: typing>=3.6.0
Dynamic: author
Dynamic: author-email
Dynamic: classifier
Dynamic: description
Dynamic: description-content-type
Dynamic: home-page
Dynamic: keywords
Dynamic: license
Dynamic: license-file
Dynamic: requires-dist
Dynamic: requires-python
Dynamic: summary
